main.v
module mips32 (
    input CLK1, CLK2 // Two-phase clock: CLK1 (Fetch, Execute, Writeback), CLK2 (Decode, Memory)
);

    // === General Purpose Register File and Memory ===
    reg [31:0] REG [0:31];         // 32 general purpose registers (32-bit each)
    reg [31:0] MEM [0:1023];       // 1024-word memory (32-bit each)

    // === Program Counter and Pipeline Registers ===
    reg [31:0] PC;                 // Program counter
    reg [31:0] IF_ID_IR, IF_ID_NPC;                 // IF/ID pipeline registers
    reg [31:0] ID_EX_A, ID_EX_B, ID_EX_IMM;         // ID/EX operand/data registers
    reg [31:0] ID_EX_IR, ID_EX_NPC;                 // ID/EX instruction and next PC
    reg [31:0] EX_MEM_ALUOUT, EX_MEM_IR, EX_MEM_B;  // EX/MEM pipeline registers
    reg [31:0] MEM_WB_LOAD_DATA, MEM_WB_ALUOUT;     // MEM/WB data from memory or ALU
    reg [31:0] MEM_WB_IR;                           // MEM/WB instruction

    // === Control Signals ===
    reg EX_MEM_COND;           // Branch condition result (from Execute stage)
    reg HALTED;                // Processor halted flag
    reg BRANCH_TAKEN;          // Branch taken flag for avoiding incorrect memory writes

    // === Instruction Type (for control decoding) ===
    reg [2:0] ID_EX_INSTRU_TYPE, EX_MEM_INSTRU_TYPE, MEM_WB_INSTRU_TYPE;

    // === Opcode Definitions ===
    parameter ADD = 6'b000000, SUB = 6'b000001, AND = 6'b000010, OR = 6'b000011;
    parameter SLT = 6'b000100, MUL = 6'b000101, HLT = 6'b111111;
    parameter LW  = 6'b001000, SW = 6'b001001;
    parameter ADDI=6'b001010, SUBI=6'b001011, SLTI=6'b001100;
    parameter BNEQZ=6'b001101, BEQZ=6'b001110;

    // === Instruction Type Classification ===
    parameter RR_ALU = 3'b000, RM_ALU = 3'b001, LOAD = 3'b010;
    parameter STORE  = 3'b011, BRANCH = 3'b100, HALT = 3'b101;

    // === Instruction Fetch Stage (IF) ===
    // Triggered on CLK1. Fetches instruction and calculates NPC.
    always @(posedge CLK1) begin
        if (!HALTED) begin
            if ((EX_MEM_IR[31:26] == BEQZ && EX_MEM_COND) || (EX_MEM_IR[31:26] == BNEQZ && !EX_MEM_COND))begin
                // Branch taken: override PC with target address
                IF_ID_IR <= MEM[EX_MEM_ALUOUT];
                PC <= EX_MEM_ALUOUT+1;
                IF_ID_NPC <= EX_MEM_ALUOUT + 1;
                BRANCH_TAKEN <= 1'b1;
            end else begin
                // Normal fetch
                IF_ID_IR <= MEM[PC];
                IF_ID_NPC <= PC + 1;
                PC <= PC + 1;
                BRANCH_TAKEN <= 1'b0;
            end
        end
    end

    // === Instruction Decode Stage (ID) ===
    // Triggered on CLK2. Decodes opcode, fetches operands, calculates immediate.
    always @(posedge CLK2) begin
        if (!HALTED) begin
            ID_EX_IR <= IF_ID_IR;
            ID_EX_NPC <= IF_ID_NPC;

            // Register operands[REG[0] IS FIXED TO 32'b0]
            if(IF_ID_IR[25:21]==5'b00000)ID_EX_A <=32'b0;
            else ID_EX_A <= REG[IF_ID_IR[25:21]];
            if(IF_ID_IR[20:16]==5'b00000)ID_EX_B <=32'b0;
            else ID_EX_B <= REG[IF_ID_IR[20:16]];

            // Sign-extended immediate value to 32-bits
            ID_EX_IMM <= {{16{IF_ID_IR[15]}}, IF_ID_IR[15:0]};

            // Determine instruction type for control
            case (IF_ID_IR[31:26])
                ADD, SUB, AND, OR, SLT, MUL : ID_EX_INSTRU_TYPE <= RR_ALU;//REGISTER-REGISTER TYPE INSTRUCTION
                ADDI, SUBI, SLTI            : ID_EX_INSTRU_TYPE <= RM_ALU;//REGISTER-IMMEDIATE TYPE INSTRUCTION
                LW                          : ID_EX_INSTRU_TYPE <= LOAD;//REGISTER-IMMEDIATE TYPE INSTRUCTION
                SW                          : ID_EX_INSTRU_TYPE <= STORE;//REGISTER-IMMEDIATE TYPE INSTRUCTION
                BEQZ,BNEQZ                  : ID_EX_INSTRU_TYPE <= BRANCH;//REGISTER-IMMEDIATE TYPE INSTRUCTION
                HLT                         : ID_EX_INSTRU_TYPE <= HALT;//REGISTER-IMMEDIATE TYPE INSTRUCTION
                default                     : ID_EX_INSTRU_TYPE <= HALT; // Treat unknown as halt
            endcase
        end
    end

    // === Execute Stage (EX) ===
    // Triggered on CLK1. Performs ALU operations, address calculation, and branch evaluation.
    always @(posedge CLK1) begin
        if (!HALTED) begin
            EX_MEM_IR <= ID_EX_IR;
            EX_MEM_INSTRU_TYPE <= ID_EX_INSTRU_TYPE;
            BRANCH_TAKEN <= 1'b0;

            case (ID_EX_INSTRU_TYPE)
                RR_ALU: begin
                    case (ID_EX_IR[31:26])
                        ADD: EX_MEM_ALUOUT <= ID_EX_A + ID_EX_B;
                        SUB: EX_MEM_ALUOUT <= ID_EX_A - ID_EX_B;
                        MUL: EX_MEM_ALUOUT <= ID_EX_A * ID_EX_B;
                        SLT: EX_MEM_ALUOUT <= (ID_EX_A < ID_EX_B) ? 32'd1 : 32'd0;
                        AND: EX_MEM_ALUOUT <= ID_EX_A & ID_EX_B;
                        OR : EX_MEM_ALUOUT <= ID_EX_A | ID_EX_B;
                        default: EX_MEM_ALUOUT <= 32'hxxxxxxxx;
                    endcase
                end

                RM_ALU: begin
                    case (ID_EX_IR[31:26])
                        ADDI: EX_MEM_ALUOUT <= ID_EX_A + ID_EX_IMM;
                        SUBI: EX_MEM_ALUOUT <= ID_EX_A - ID_EX_IMM;
                        SLTI: EX_MEM_ALUOUT <= (ID_EX_A < ID_EX_IMM) ? 32'd1 : 32'd0;
                        default: EX_MEM_ALUOUT <= 32'hxxxxxxxx;
                    endcase
                end

                LOAD, STORE: begin
                    // Compute effective memory address
                    EX_MEM_ALUOUT <= ID_EX_A + ID_EX_IMM;
                    EX_MEM_B <= ID_EX_B;
                end

                BRANCH: begin
                    EX_MEM_COND <= (ID_EX_A == 0); // Only for BEQZ and BNEQZ here
                    EX_MEM_ALUOUT <= ID_EX_NPC + ID_EX_IMM;
                end
            endcase
        end
    end

    // === Memory Access Stage (MEM) ===
    // Triggered on CLK2. Performs memory read/write if required.
    always @(posedge CLK2) begin
        if (!HALTED) begin
            MEM_WB_IR <= EX_MEM_IR;
            MEM_WB_INSTRU_TYPE <= EX_MEM_INSTRU_TYPE;

            case (EX_MEM_INSTRU_TYPE)
                RR_ALU, RM_ALU: begin
                    MEM_WB_ALUOUT <= EX_MEM_ALUOUT;
                end
                LOAD: begin
                    MEM_WB_LOAD_DATA <= MEM[EX_MEM_ALUOUT]; // Load from memory
                end
                STORE: begin
                    if (!BRANCH_TAKEN) MEM[EX_MEM_ALUOUT] <= EX_MEM_B; // Avoid storing after branch taken
                end
            endcase
        end
    end

    // === Writeback Stage (WB) ===
    // Triggered on CLK1. Writes results to registers or halts processor.
    always @(posedge CLK1) begin
        if (!BRANCH_TAKEN) begin
            case (MEM_WB_INSTRU_TYPE)
                RR_ALU: REG[MEM_WB_IR[15:11]] <= MEM_WB_ALUOUT;
                RM_ALU: REG[MEM_WB_IR[20:16]] <= MEM_WB_ALUOUT;
                LOAD  : REG[MEM_WB_IR[20:16]] <= MEM_WB_LOAD_DATA;
                HALT  : HALTED <= 1'b1;
            endcase
        end
    end

endmodule

factorial.v
`timescale 1ps/1ps
`include "main.v"

module test();
  reg clk1, clk2;
  integer k;

  // Instantiate the processor module
  mips32 mips(clk1, clk2);

  // Clock generation block
  // clk1 and clk2 alternate with a delay of 5 time units each
  initial begin
    clk1 = 0; clk2 = 0;
    mips.HALTED=0;
    mips.BRANCH_TAKEN=0;
    mips.PC=0;

    repeat (50) begin
      #5 clk1 = 1; #5 clk1 = 0;
      #5 clk2 = 1; #5 clk2 = 0;
    end
  end

  // Test stimulus block
  initial begin
        // mips.REG[10]=200;
        mips.MEM[200]=8;
        // mips.REG[1]=1;
        mips.REG[7]=0;

        mips.MEM[0]=32'h280a00c8; // ADDI R10,R0,200
        mips.MEM[1]=32'h28010001; // ADDI R1,R0,1
        mips.MEM[2]=32'h0ce77800;//DUMMY INSTRUCTION : OR R7,R7,R7
        mips.MEM[3]=32'h21420000;//LW R2 0(R10)
        mips.MEM[4]=32'h0ce77800;//DUMMY INSTRUCTION : OR R7,R7,R7
        mips.MEM[5]=32'h14410800;//MUL R1,R2,R1
        mips.MEM[6]=32'h2c420001;//SUBI R2,R2,1
        mips.MEM[7]=32'h0ce77800;//DUMMY INSTRUCTION : OR R7,R7,R7
        mips.MEM[8]=32'h3440fffc;// BNEQZ R2,LOOP
        mips.MEM[9]=32'h2541fffe;//SW R1, -2(R10)
        mips.MEM[10]=32'hfc000000;//HLT
wait(mips.HALTED);
#10
    $display("MEM[200] : %d : MEM[198] : %d",mips.MEM[200],mips.MEM[198]);

  end

  // VCD (waveform) dump block
  initial begin
    $dumpfile("factorial.vcd");     // Output file for waveform data
    $dumpvars(0, test);        // Dump all variables in module 'test'
    $monitor("REG[1] : %d ",mips.REG[1]);
    #5000$finish;             // End simulation after 1000 time units
  end
endmodule

factorial.vcd
$date
	Tue Jun 17 02:10:08 2025
$end
$version
	Icarus Verilog
$end
$timescale
	1ps
$end
$scope module test $end
$var reg 1 ! clk1 $end
$var reg 1 " clk2 $end
$scope module mips $end
$var wire 1 ! CLK1 $end
$var wire 1 " CLK2 $end
$var parameter 6 # ADD $end
$var parameter 6 $ ADDI $end
$var parameter 6 % AND $end
$var parameter 6 & BEQZ $end
$var parameter 6 ' BNEQZ $end
$var parameter 3 ( BRANCH $end
$var parameter 3 ) HALT $end
$var parameter 6 * HLT $end
$var parameter 3 + LOAD $end
$var parameter 6 , LW $end
$var parameter 6 - MUL $end
$var parameter 6 . OR $end
$var parameter 3 / RM_ALU $end
$var parameter 3 0 RR_ALU $end
$var parameter 6 1 SLT $end
$var parameter 6 2 SLTI $end
$var parameter 3 3 STORE $end
$var parameter 6 4 SUB $end
$var parameter 6 5 SUBI $end
$var parameter 6 6 SW $end
$var reg 1 7 BRANCH_TAKEN $end
$var reg 32 8 EX_MEM_ALUOUT [31:0] $end
$var reg 32 9 EX_MEM_B [31:0] $end
$var reg 1 : EX_MEM_COND $end
$var reg 3 ; EX_MEM_INSTRU_TYPE [2:0] $end
$var reg 32 < EX_MEM_IR [31:0] $end
$var reg 1 = HALTED $end
$var reg 32 > ID_EX_A [31:0] $end
$var reg 32 ? ID_EX_B [31:0] $end
$var reg 32 @ ID_EX_IMM [31:0] $end
$var reg 3 A ID_EX_INSTRU_TYPE [2:0] $end
$var reg 32 B ID_EX_IR [31:0] $end
$var reg 32 C ID_EX_NPC [31:0] $end
$var reg 32 D IF_ID_IR [31:0] $end
$var reg 32 E IF_ID_NPC [31:0] $end
$var reg 32 F MEM_WB_ALUOUT [31:0] $end
$var reg 3 G MEM_WB_INSTRU_TYPE [2:0] $end
$var reg 32 H MEM_WB_IR [31:0] $end
$var reg 32 I MEM_WB_LOAD_DATA [31:0] $end
$var reg 32 J PC [31:0] $end
$upscope $end
$upscope $end
$enddefinitions $end
$comment Show the parameter values. $end
$dumpall
b1001 6
b1011 5
b1 4
b11 3
b1100 2
b100 1
b0 0
b1 /
b11 .
b101 -
b1000 ,
b10 +
b111111 *
b101 )
b100 (
b1101 '
b1110 &
b10 %
b1010 $
b0 #
$end
#0
$dumpvars
b0 J
bx I
bx H
bx G
bx F
bx E
bx D
bx C
bx B
bx A
bx @
bx ?
bx >
0=
bx <
bx ;
x:
bx 9
bx 8
07
0"
0!
$end
#5
b1 J
b1 E
b101000000010100000000011001000 D
1!
#10
0!
#15
b1 A
b11001000 @
b0 >
b1 C
b101000000010100000000011001000 B
1"
#20
0"
#25
b11001000 8
b1 ;
b101000000010100000000011001000 <
b10 J
b10 E
b101000000000010000000000000001 D
1!
#30
0!
#35
b11001000 F
b1 G
b101000000010100000000011001000 H
b1 @
b10 C
b101000000000010000000000000001 B
1"
#40
0"
#45
b11 J
b11 E
b1100111001110111100000000000 D
b1 8
b101000000000010000000000000001 <
1!
#50
0!
#55
b0 A
b111100000000000 @
b0 ?
b11 C
b1100111001110111100000000000 B
b1 F
b101000000000010000000000000001 H
1"
#60
0"
#65
b0 8
b0 ;
b1100111001110111100000000000 <
b100 J
b100 E
b100001010000100000000000000000 D
1!
#70
0!
#75
b0 F
b0 G
b1100111001110111100000000000 H
b10 A
b0 @
bx ?
b11001000 >
b100 C
b100001010000100000000000000000 B
1"
#80
0"
#85
b101 J
b101 E
b1100111001110111100000000000 D
b11001000 8
b10 ;
b100001010000100000000000000000 <
1!
#90
0!
#95
b0 A
b111100000000000 @
b0 ?
b0 >
b101 C
b1100111001110111100000000000 B
b1000 I
b10 G
b100001010000100000000000000000 H
1"
#100
0"
#105
b0 8
b0 ;
b1100111001110111100000000000 <
b110 J
b110 E
b10100010000010000100000000000 D
1!
#110
0!
#115
b0 G
b1100111001110111100000000000 H
b100000000000 @
b1 ?
b1000 >
b110 C
b10100010000010000100000000000 B
1"
#120
0"
#125
b111 J
b111 E
b101100010000100000000000000001 D
b1000 8
b10100010000010000100000000000 <
1!
#130
0!
#135
b1 A
b1 @
b1000 ?
b111 C
b101100010000100000000000000001 B
b1000 F
b10100010000010000100000000000 H
1"
#140
0"
#145
b111 8
b1 ;
b101100010000100000000000000001 <
b1000 J
b1000 E
b1100111001110111100000000000 D
1!
#150
0!
#155
b111 F
b1 G
b101100010000100000000000000001 H
b0 A
b111100000000000 @
b0 ?
b0 >
b1000 C
b1100111001110111100000000000 B
1"
#160
0"
#165
b1001 J
b1001 E
b110100010000001111111111111100 D
b0 8
b0 ;
b1100111001110111100000000000 <
1!
#170
0!
#175
b100 A
b11111111111111111111111111111100 @
b111 >
b1001 C
b110100010000001111111111111100 B
b0 F
b0 G
b1100111001110111100000000000 H
1"
#180
0"
#185
b101 8
0:
b100 ;
b110100010000001111111111111100 <
b1010 J
b1010 E
b100101010000011111111111111110 D
1!
#190
0!
#195
b100 G
b110100010000001111111111111100 H
b11 A
b11111111111111111111111111111110 @
b1000 ?
b11001000 >
b1010 C
b100101010000011111111111111110 B
1"
#200
0"
#205
17
b110 E
b110 J
b10100010000010000100000000000 D
b1000 9
b11000110 8
b11 ;
b100101010000011111111111111110 <
1!
#210
0!
#215
b0 A
b100000000000 @
b111 >
b110 C
b10100010000010000100000000000 B
b11 G
b100101010000011111111111111110 H
1"
#220
0"
#225
b111000 8
b0 ;
b10100010000010000100000000000 <
07
b111 J
b111 E
b101100010000100000000000000001 D
1!
#230
0!
#235
b111000 F
b0 G
b10100010000010000100000000000 H
b1 A
b1 @
b111 ?
b111 C
b101100010000100000000000000001 B
1"
#240
0"
#245
b1000 J
b1000 E
b1100111001110111100000000000 D
b110 8
b1 ;
b101100010000100000000000000001 <
1!
#250
0!
#255
b0 A
b111100000000000 @
b0 ?
b0 >
b1000 C
b1100111001110111100000000000 B
b110 F
b1 G
b101100010000100000000000000001 H
1"
#260
0"
#265
b0 8
b0 ;
b1100111001110111100000000000 <
b1001 J
b1001 E
b110100010000001111111111111100 D
1!
#270
0!
#275
b0 F
b0 G
b1100111001110111100000000000 H
b100 A
b11111111111111111111111111111100 @
b110 >
b1001 C
b110100010000001111111111111100 B
1"
#280
0"
#285
b1010 J
b1010 E
b100101010000011111111111111110 D
b101 8
b100 ;
b110100010000001111111111111100 <
1!
#290
0!
#295
b11 A
b11111111111111111111111111111110 @
b111000 ?
b11001000 >
b1010 C
b100101010000011111111111111110 B
b100 G
b110100010000001111111111111100 H
1"
#300
0"
#305
b111000 9
b11000110 8
b11 ;
b100101010000011111111111111110 <
07
b110 E
b110 J
b10100010000010000100000000000 D
1!
#310
0!
#315
b11 G
b100101010000011111111111111110 H
b0 A
b100000000000 @
b110 >
b110 C
b10100010000010000100000000000 B
1"
#320
0"
#325
b111 J
b111 E
b101100010000100000000000000001 D
b101010000 8
b0 ;
b10100010000010000100000000000 <
1!
#330
0!
#335
b1 A
b1 @
b110 ?
b111 C
b101100010000100000000000000001 B
b101010000 F
b0 G
b10100010000010000100000000000 H
1"
#340
0"
#345
b101 8
b1 ;
b101100010000100000000000000001 <
b1000 J
b1000 E
b1100111001110111100000000000 D
1!
#350
0!
#355
b101 F
b1 G
b101100010000100000000000000001 H
b0 A
b111100000000000 @
b0 ?
b0 >
b1000 C
b1100111001110111100000000000 B
1"
#360
0"
#365
b1001 J
b1001 E
b110100010000001111111111111100 D
b0 8
b0 ;
b1100111001110111100000000000 <
1!
#370
0!
#375
b100 A
b11111111111111111111111111111100 @
b101 >
b1001 C
b110100010000001111111111111100 B
b0 F
b0 G
b1100111001110111100000000000 H
1"
#380
0"
#385
b101 8
b100 ;
b110100010000001111111111111100 <
b1010 J
b1010 E
b100101010000011111111111111110 D
1!
#390
0!
#395
b100 G
b110100010000001111111111111100 H
b11 A
b11111111111111111111111111111110 @
b101010000 ?
b11001000 >
b1010 C
b100101010000011111111111111110 B
1"
#400
0"
#405
17
b110 E
b110 J
b10100010000010000100000000000 D
b101010000 9
b11000110 8
b11 ;
b100101010000011111111111111110 <
1!
#410
0!
#415
b0 A
b100000000000 @
b101 >
b110 C
b10100010000010000100000000000 B
b11 G
b100101010000011111111111111110 H
1"
#420
0"
#425
b11010010000 8
b0 ;
b10100010000010000100000000000 <
07
b111 J
b111 E
b101100010000100000000000000001 D
1!
#430
0!
#435
b11010010000 F
b0 G
b10100010000010000100000000000 H
b1 A
b1 @
b101 ?
b111 C
b101100010000100000000000000001 B
1"
#440
0"
#445
b1000 J
b1000 E
b1100111001110111100000000000 D
b100 8
b1 ;
b101100010000100000000000000001 <
1!
#450
0!
#455
b0 A
b111100000000000 @
b0 ?
b0 >
b1000 C
b1100111001110111100000000000 B
b100 F
b1 G
b101100010000100000000000000001 H
1"
#460
0"
#465
b0 8
b0 ;
b1100111001110111100000000000 <
b1001 J
b1001 E
b110100010000001111111111111100 D
1!
#470
0!
#475
b0 F
b0 G
b1100111001110111100000000000 H
b100 A
b11111111111111111111111111111100 @
b100 >
b1001 C
b110100010000001111111111111100 B
1"
#480
0"
#485
b1010 J
b1010 E
b100101010000011111111111111110 D
b101 8
b100 ;
b110100010000001111111111111100 <
1!
#490
0!
#495
b11 A
b11111111111111111111111111111110 @
b11010010000 ?
b11001000 >
b1010 C
b100101010000011111111111111110 B
b100 G
b110100010000001111111111111100 H
1"
#500
0"
#505
b11010010000 9
b11000110 8
b11 ;
b100101010000011111111111111110 <
07
b110 E
b110 J
b10100010000010000100000000000 D
1!
#510
0!
#515
b11 G
b100101010000011111111111111110 H
b0 A
b100000000000 @
b100 >
b110 C
b10100010000010000100000000000 B
1"
#520
0"
#525
b111 J
b111 E
b101100010000100000000000000001 D
b1101001000000 8
b0 ;
b10100010000010000100000000000 <
1!
#530
0!
#535
b1 A
b1 @
b100 ?
b111 C
b101100010000100000000000000001 B
b1101001000000 F
b0 G
b10100010000010000100000000000 H
1"
#540
0"
#545
b11 8
b1 ;
b101100010000100000000000000001 <
b1000 J
b1000 E
b1100111001110111100000000000 D
1!
#550
0!
#555
b11 F
b1 G
b101100010000100000000000000001 H
b0 A
b111100000000000 @
b0 ?
b0 >
b1000 C
b1100111001110111100000000000 B
1"
#560
0"
#565
b1001 J
b1001 E
b110100010000001111111111111100 D
b0 8
b0 ;
b1100111001110111100000000000 <
1!
#570
0!
#575
b100 A
b11111111111111111111111111111100 @
b11 >
b1001 C
b110100010000001111111111111100 B
b0 F
b0 G
b1100111001110111100000000000 H
1"
#580
0"
#585
b101 8
b100 ;
b110100010000001111111111111100 <
b1010 J
b1010 E
b100101010000011111111111111110 D
1!
#590
0!
#595
b100 G
b110100010000001111111111111100 H
b11 A
b11111111111111111111111111111110 @
b1101001000000 ?
b11001000 >
b1010 C
b100101010000011111111111111110 B
1"
#600
0"
#605
17
b110 E
b110 J
b10100010000010000100000000000 D
b1101001000000 9
b11000110 8
b11 ;
b100101010000011111111111111110 <
1!
#610
0!
#615
b0 A
b100000000000 @
b11 >
b110 C
b10100010000010000100000000000 B
b11 G
b100101010000011111111111111110 H
1"
#620
0"
#625
b100111011000000 8
b0 ;
b10100010000010000100000000000 <
07
b111 J
b111 E
b101100010000100000000000000001 D
1!
#630
0!
#635
b100111011000000 F
b0 G
b10100010000010000100000000000 H
b1 A
b1 @
b11 ?
b111 C
b101100010000100000000000000001 B
1"
#640
0"
#645
b1000 J
b1000 E
b1100111001110111100000000000 D
b10 8
b1 ;
b101100010000100000000000000001 <
1!
#650
0!
#655
b0 A
b111100000000000 @
b0 ?
b0 >
b1000 C
b1100111001110111100000000000 B
b10 F
b1 G
b101100010000100000000000000001 H
1"
#660
0"
#665
b0 8
b0 ;
b1100111001110111100000000000 <
b1001 J
b1001 E
b110100010000001111111111111100 D
1!
#670
0!
#675
b0 F
b0 G
b1100111001110111100000000000 H
b100 A
b11111111111111111111111111111100 @
b10 >
b1001 C
b110100010000001111111111111100 B
1"
#680
0"
#685
b1010 J
b1010 E
b100101010000011111111111111110 D
b101 8
b100 ;
b110100010000001111111111111100 <
1!
#690
0!
#695
b11 A
b11111111111111111111111111111110 @
b100111011000000 ?
b11001000 >
b1010 C
b100101010000011111111111111110 B
b100 G
b110100010000001111111111111100 H
1"
#700
0"
#705
b100111011000000 9
b11000110 8
b11 ;
b100101010000011111111111111110 <
07
b110 E
b110 J
b10100010000010000100000000000 D
1!
#710
0!
#715
b11 G
b100101010000011111111111111110 H
b0 A
b100000000000 @
b10 >
b110 C
b10100010000010000100000000000 B
1"
#720
0"
#725
b111 J
b111 E
b101100010000100000000000000001 D
b1001110110000000 8
b0 ;
b10100010000010000100000000000 <
1!
#730
0!
#735
b1 A
b1 @
b10 ?
b111 C
b101100010000100000000000000001 B
b1001110110000000 F
b0 G
b10100010000010000100000000000 H
1"
#740
0"
#745
b1 8
b1 ;
b101100010000100000000000000001 <
b1000 J
b1000 E
b1100111001110111100000000000 D
1!
#750
0!
#755
b1 F
b1 G
b101100010000100000000000000001 H
b0 A
b111100000000000 @
b0 ?
b0 >
b1000 C
b1100111001110111100000000000 B
1"
#760
0"
#765
b1001 J
b1001 E
b110100010000001111111111111100 D
b0 8
b0 ;
b1100111001110111100000000000 <
1!
#770
0!
#775
b100 A
b11111111111111111111111111111100 @
b1 >
b1001 C
b110100010000001111111111111100 B
b0 F
b0 G
b1100111001110111100000000000 H
1"
#780
0"
#785
b101 8
b100 ;
b110100010000001111111111111100 <
b1010 J
b1010 E
b100101010000011111111111111110 D
1!
#790
0!
#795
b100 G
b110100010000001111111111111100 H
b11 A
b11111111111111111111111111111110 @
b1001110110000000 ?
b11001000 >
b1010 C
b100101010000011111111111111110 B
1"
#800
0"
#805
17
b110 E
b110 J
b10100010000010000100000000000 D
b1001110110000000 9
b11000110 8
b11 ;
b100101010000011111111111111110 <
1!
#810
0!
#815
b0 A
b100000000000 @
b1 >
b110 C
b10100010000010000100000000000 B
b11 G
b100101010000011111111111111110 H
1"
#820
0"
#825
b1001110110000000 8
b0 ;
b10100010000010000100000000000 <
07
b111 J
b111 E
b101100010000100000000000000001 D
1!
#830
0!
#835
b1001110110000000 F
b0 G
b10100010000010000100000000000 H
b1 A
b1 @
b1 ?
b111 C
b101100010000100000000000000001 B
1"
#840
0"
#845
b1000 J
b1000 E
b1100111001110111100000000000 D
b0 8
b1 ;
b101100010000100000000000000001 <
1!
#850
0!
#855
b0 A
b111100000000000 @
b0 ?
b0 >
b1000 C
b1100111001110111100000000000 B
b0 F
b1 G
b101100010000100000000000000001 H
1"
#860
0"
#865
b0 ;
b1100111001110111100000000000 <
b1001 J
b1001 E
b110100010000001111111111111100 D
1!
#870
0!
#875
b0 G
b1100111001110111100000000000 H
b100 A
b11111111111111111111111111111100 @
b1001 C
b110100010000001111111111111100 B
1"
#880
0"
#885
b1010 J
b1010 E
b100101010000011111111111111110 D
b101 8
1:
b100 ;
b110100010000001111111111111100 <
1!
#890
0!
#895
b11 A
b11111111111111111111111111111110 @
b1001110110000000 ?
b11001000 >
b1010 C
b100101010000011111111111111110 B
b100 G
b110100010000001111111111111100 H
1"
#900
0"
#905
b11000110 8
b11 ;
b100101010000011111111111111110 <
b1011 J
b1011 E
b11111100000000000000000000000000 D
1!
#910
0!
#915
b11 G
b100101010000011111111111111110 H
b101 A
b0 @
b0 ?
b0 >
b1011 C
b11111100000000000000000000000000 B
1"
#920
0"
#925
b1100 J
b1100 E
bx D
b101 ;
b11111100000000000000000000000000 <
1!
#930
0!
#935
bx @
bx ?
bx >
b1100 C
bx B
b101 G
b11111100000000000000000000000000 H
1"
#940
0"
#945
1=
bx <
b1101 J
b1101 E
1!
